LICENSE
MANIFEST.in
README.rst
setup.py
django_hatstall.egg-info/PKG-INFO
django_hatstall.egg-info/SOURCES.txt
django_hatstall.egg-info/dependency_links.txt
django_hatstall.egg-info/requires.txt
django_hatstall.egg-info/top_level.txt
hatstall/__init__.py
hatstall/apps.py
hatstall/tests.py
hatstall/urls.py
hatstall/views.py
hatstall/templates/about.html
hatstall/templates/organizations.html
hatstall/templates/profile.html
hatstall/templates/profiles.html
hatstall/templates/shdb_form.html