Metadata-Version: 1.1
Name: django-hatstall
Version: 0.1
Summary: A Django app to manage identities in Sorting Hat.
Home-page: https://github.com/chaoss/grimoirelab-hatstall
Author: Bitergia
Author-email: acs@bitergia.com
License: GPLv3
Keywords: development repositories analytics git github bugzilla jira jenkins
Platform: UNKNOWN
Classifier: Environment :: Web Environment
Classifier: Framework :: Django
Classifier: Framework :: Django :: 2.0
Classifier: Intended Audience :: Customer Service
Classifier: License :: OSI Approved :: GNU General Public License v3 (GPLv3)
Classifier: Operating System :: OS Independent
Classifier: Programming Language :: Python
Classifier: Programming Language :: Python :: 3.5
Classifier: Programming Language :: Python :: 3.6
Classifier: Topic :: Internet :: WWW/HTTP
Classifier: Topic :: Internet :: WWW/HTTP :: Dynamic Content
